README.md
setup.py
src/PyGetWindow.egg-info/PKG-INFO
src/PyGetWindow.egg-info/SOURCES.txt
src/PyGetWindow.egg-info/dependency_links.txt
src/PyGetWindow.egg-info/requires.txt
src/PyGetWindow.egg-info/top_level.txt
src/pygetwindow/__init__.py
src/pygetwindow/_pygetwindow_win.py
src/pygetwindow/foo.py
src/pygetwindow.egg-info/PKG-INFO
src/pygetwindow.egg-info/SOURCES.txt
src/pygetwindow.egg-info/dependency_links.txt
src/pygetwindow.egg-info/top_level.txt