Metadata-Version: 2.1
Name: PyGetWindow
Version: 0.0.2
Summary: A simple, cross-platform module for obtaining GUI information on application's windows.
Home-page: https://github.com/asweigart/pygetwindow
Author: Al Sweigart
Author-email: al@inventwithpython.com
License: BSD
Keywords: gui window geometry resize minimize maximize close title
Platform: UNKNOWN
Classifier: Development Status :: 4 - Beta
Classifier: Environment :: Win32 (MS Windows)
Classifier: Environment :: X11 Applications
Classifier: Environment :: MacOS X
Classifier: Intended Audience :: Developers
Classifier: License :: OSI Approved :: BSD License
Classifier: Operating System :: OS Independent
Classifier: Programming Language :: Python
Classifier: Programming Language :: Python :: 2
Classifier: Programming Language :: Python :: 2.7
Classifier: Programming Language :: Python :: 3
Classifier: Programming Language :: Python :: 3.4
Classifier: Programming Language :: Python :: 3.5
Classifier: Programming Language :: Python :: 3.6
Classifier: Programming Language :: Python :: 3.7
